bayesian_networks_rey20074/BayesianNetwork.py
bayesian_networks_rey20074/__init__.py
bayesian_networks_rey20074-0.1.5.dist-info/LICENSE
bayesian_networks_rey20074-0.1.5.dist-info/METADATA
bayesian_networks_rey20074-0.1.5.dist-info/WHEEL
bayesian_networks_rey20074-0.1.5.dist-info/top_level.txt
bayesian_networks_rey20074-0.1.5.dist-info/RECORD
