Metadata-Version: 2.1
Name: bayesian_networks_rey20074
Version: 0.1.5
Summary: Una libreria para construir redes bayesianas y realizar inferencia probabilística
Home-page: https://github.com/JuanCarlosBajan/UVG-IA-lab2
Author: Grupo 5
Author-email: josemarianoreyesh02@gmail.com
Classifier: Programming Language :: Python :: 3
Classifier: License :: OSI Approved :: MIT License
Classifier: Operating System :: OS Independent
Requires-Python: >=3.6
License-File: LICENSE
